kimbundu_speech_ai/__init__.py
kimbundu_speech_ai/analyze_audio_lengths.py
kimbundu_speech_ai/audio_processing.py
kimbundu_speech_ai/check_stereo.py
kimbundu_speech_ai/convert_to_int16.py
kimbundu_speech_ai/convert_to_mono.py
kimbundu_speech_ai/create_full_filelist.py
kimbundu_speech_ai/create_proper_validation_filelist.py
kimbundu_speech_ai/data_utils.py
kimbundu_speech_ai/debug_audio.py
kimbundu_speech_ai/debug_problematic.py
kimbundu_speech_ai/debug_specific.py
kimbundu_speech_ai/debug_stft.py
kimbundu_speech_ai/debug_tensor_shape.py
kimbundu_speech_ai/debug_test.py
kimbundu_speech_ai/debug_test2.py
kimbundu_speech_ai/distributed.py
kimbundu_speech_ai/filter_filelist.py
kimbundu_speech_ai/fix_validation_filelist.py
kimbundu_speech_ai/hparams.py
kimbundu_speech_ai/layers.py
kimbundu_speech_ai/logger.py
kimbundu_speech_ai/loss_function.py
kimbundu_speech_ai/loss_scaler.py
kimbundu_speech_ai/model.py
kimbundu_speech_ai/multiproc.py
kimbundu_speech_ai/plotting_utils.py
kimbundu_speech_ai/resample_wavs.py
kimbundu_speech_ai/split_filelist.py
kimbundu_speech_ai/stft.py
kimbundu_speech_ai/stft_fixed.py
kimbundu_speech_ai/stt.py
kimbundu_speech_ai/synthesize.py
kimbundu_speech_ai/synthetizer.py
kimbundu_speech_ai/tts.py
kimbundu_speech_ai/utils.py
kimbundu_speech_ai/vocode.py
kimbundu_speech_ai/text/__init__.py
kimbundu_speech_ai/text/cleaners.py
kimbundu_speech_ai/text/cmudict.py
kimbundu_speech_ai/text/numbers.py
kimbundu_speech_ai/text/symbols.py
kimbundu_speech_ai/waveglow/__init__.py
kimbundu_speech_ai/waveglow/convert_model.py
kimbundu_speech_ai/waveglow/denoiser.py
kimbundu_speech_ai/waveglow/distributed.py
kimbundu_speech_ai/waveglow/glow.py
kimbundu_speech_ai/waveglow/glow_old.py
kimbundu_speech_ai/waveglow/inference.py
kimbundu_speech_ai/waveglow/mel2samp.py
kimbundu_speech_ai/waveglow/train.py
kimbundu_speech_ai-0.0.1.dist-info/licenses/LICENSE
kimbundu_speech_ai-0.0.1.dist-info/METADATA
kimbundu_speech_ai-0.0.1.dist-info/WHEEL
kimbundu_speech_ai-0.0.1.dist-info/top_level.txt
kimbundu_speech_ai-0.0.1.dist-info/RECORD
