Metadata-Version: 2.4
Name: kimbundu_speech_ai
Version: 0.0.1
Summary: A Python library for Speech-to-Text and Text-to-Speech in Kimbundu, created to promote language inclusion and support the preservation of an under-represented African language.
Author-email: Ricardo Sabino <rcarvalhosabino@gmail.com>
License: Academic Non-Commercial License
Classifier: Programming Language :: Python :: 3
Classifier: Programming Language :: Python :: Implementation :: CPython
Classifier: Programming Language :: Python :: Implementation :: PyPy
Requires-Python: >=3.8
License-File: LICENSE
Requires-Dist: numpy
Requires-Dist: torch>=1.9
Requires-Dist: librosa
Requires-Dist: soundfile
Requires-Dist: unidecode
Requires-Dist: inflect
Requires-Dist: transformers
Dynamic: license-file
